setup.py
dsnd_probability/Binomialdistribution.py
dsnd_probability/Gaussiandistribution.py
dsnd_probability/Generaldistribution.py
dsnd_probability/__init__.py
dsnd_probability_vsari.egg-info/PKG-INFO
dsnd_probability_vsari.egg-info/SOURCES.txt
dsnd_probability_vsari.egg-info/dependency_links.txt
dsnd_probability_vsari.egg-info/not-zip-safe
dsnd_probability_vsari.egg-info/top_level.txt