Metadata-Version: 1.0
Name: dsnd-probability-vsari
Version: 0.1
Summary: Gaussian & Binomial distributions
Home-page: UNKNOWN
Author: Veli Sari
Author-email: veli.sari@gmail.com
License: UNKNOWN
Platform: UNKNOWN
